MANIFEST.in
README.rst
setup.py
beget/__init__.py
beget/beget.py
beget/tests.py
beget.egg-info/PKG-INFO
beget.egg-info/SOURCES.txt
beget.egg-info/dependency_links.txt
beget.egg-info/not-zip-safe
beget.egg-info/top_level.txt
beget/project_template/.gitignore
beget/project_template/setup.py
beget/project_template/project/__init__.py
beget/project_template/project/settings.py
beget/project_template/project/urls.py
bin/beget