Metadata-Version: 1.0
Name: beget
Version: 0.1.3
Summary: Django project generator
Home-page: http://github.com/rob-b/Beget
Author: Rob Berry
Author-email: UNKNOWN
License: BSD
Platform: UNKNOWN
Classifier: Programming Language :: Python
Classifier: Framework :: Django
Classifier: Topic :: Internet :: WWW/HTTP
